pytest_trello
