Metadata-Version: 1.1
Name: pytest-trello
Version: 0.0.4
Summary: Plugin for py.test that integrates trello using markers
Home-page: http://github.com/jlaska/pytest-trello
Author: James Laska
Author-email: <jlaska@ansible.com>
License: MIT
Keywords: py.test pytest trello
Platform: any
Classifier: Development Status :: 5 - Production/Stable
Classifier: Intended Audience :: Developers
Classifier: License :: OSI Approved :: MIT License
Classifier: Operating System :: OS Independent
Classifier: Topic :: Software Development :: Testing
Classifier: Topic :: Software Development :: Quality Assurance
Classifier: Topic :: Utilities
Classifier: Programming Language :: Python
Classifier: Programming Language :: Python :: 2
Classifier: Programming Language :: Python :: 2.6
Classifier: Programming Language :: Python :: 2.7 
Classifier: Programming Language :: Python :: 3
Classifier: Programming Language :: Python :: 3.4
